FaceChannel/__init__.py
FaceChannel/FaceChannelV1/FaceChannelV1.py
FaceChannel/FaceChannelV1/__init__.py
FaceChannel/FaceChannelV1/imageProcessingUtil.py
FaceChannel/FaceChannelV1/TrainedNetworks/__init__.py
FaceChannel/FaceChannelV1/TrainedNetworks/faceDetector/__init__.py
FaceChannel/Metrics/__init__.py
FaceChannel/Metrics/metrics.py
FaceChannel/SelfAffectiveMemory/SelfAffectiveMemory.py
FaceChannel/SelfAffectiveMemory/Standard_GWR.py
FaceChannel/SelfAffectiveMemory/__init__.py
FaceChannel-0.0.3.4.dist-info/LICENSE
FaceChannel-0.0.3.4.dist-info/METADATA
FaceChannel-0.0.3.4.dist-info/WHEEL
FaceChannel-0.0.3.4.dist-info/top_level.txt
FaceChannel-0.0.3.4.dist-info/RECORD
